Metadata-Version: 2.1
Name: cmakeutils
Version: 1.9.2
Summary: Helper functions with CMake
Home-page: https://github.com/scivision/cmakeutils
Author: Michael Hirsch, Ph.D.
Author-email: scivision@users.noreply.github.com
License: UNKNOWN
Keywords: CMake
Platform: UNKNOWN
Classifier: Development Status :: 5 - Production/Stable
Classifier: Environment :: Console
Classifier: Operating System :: OS Independent
Classifier: Programming Language :: Python :: 3
Classifier: Topic :: Utilities
Requires-Python: >=3.7
Provides-Extra: tests
Provides-Extra: lint
License-File: LICENSE.txt
